{"P4": {"labels": ["documentation"], "postTitle": "F12", "postUrl": "post/F12.html", "createdDate": "2025-04-14", "dateLabelColor": "#0969da"}, "P2": {"labels": ["documentation"], "postTitle": "http\u534f\u8bae\uff08 \u8865\uff09", "postUrl": "post/http-xie-yi-%EF%BC%88%20-bu-%EF%BC%89.html", "createdDate": "2025-04-13", "dateLabelColor": "#0969da"}, "labelColorDict": {"bug": "#d73a4a", "documentation": "#0075ca", "duplicate": "#cfd3d7", "enhancement": "#a2eeef", "good first issue": "#7057ff", "help wanted": "#008672", "invalid": "#e4e669", "question": "#d876e3", "wontfix": "#ffffff"}}